adit_client/__init__.py
adit_client/client.py
adit_client/utils/__init__.py
adit_client/utils/testing_helpers.py
adit_client-0.46.0.dist-info/METADATA
adit_client-0.46.0.dist-info/WHEEL
adit_client-0.46.0.dist-info/RECORD
