Metadata-Version: 2.4
Name: adit-client
Version: 0.46.0
Summary: ADIT Client library to connect to an ADIT server.
Author: Kai Schlamp
License-Expression: AGPL-3.0-or-later
Requires-Python: <4.0,>=3.12
Requires-Dist: dicognito>=0.17.0
Requires-Dist: dicomweb-client>=0.59.3
Requires-Dist: pydicom>=2.4.4
